pgcrypto/__init__.py
pgcrypto/fields.py
pgcrypto/lookups.py
pgcrypto/mixins.py
pgcrypto/models.py
pgcrypto/migrations/0001_add_pgcrypto_extension.py
pgcrypto/migrations/__init__.py
tests/default/__init__.py
tests/diff_keys/__init__.py
tests/diff_keys/models.py
django_pgcrypto_fields-2.6.0.dist-info/AUTHORS.md
django_pgcrypto_fields-2.6.0.dist-info/LICENSE
django_pgcrypto_fields-2.6.0.dist-info/METADATA
django_pgcrypto_fields-2.6.0.dist-info/WHEEL
django_pgcrypto_fields-2.6.0.dist-info/top_level.txt
django_pgcrypto_fields-2.6.0.dist-info/RECORD
