Metadata-Version: 2.1
Name: django-pgcrypto-fields
Version: 2.6.0
Summary: Encrypted fields for Django dealing with pgcrypto postgres extension.
Home-page: https://github.com/incuna/django-pgcrypto-fields
Author: Incuna Ltd
Author-email: admin@incuna.com
License: BSD
Platform: UNKNOWN
Classifier: Development Status :: 5 - Production/Stable
Classifier: Framework :: Django
Classifier: Intended Audience :: Developers
Classifier: License :: OSI Approved :: BSD License
Classifier: Natural Language :: English
Classifier: Programming Language :: Python
Classifier: Programming Language :: Python :: 3
Classifier: Programming Language :: Python :: 3.6
Classifier: Programming Language :: Python :: 3.7
Classifier: Programming Language :: Python :: 3.8
Classifier: Programming Language :: Python :: 3 :: Only
Classifier: Topic :: Database
Classifier: Topic :: Security :: Cryptography
Requires-Python: >=3.6
